LICENSE
MANIFEST.in
README.md
requirements.txt
setup.cfg
setup.py
assets/__init__.py
assets/constants.py
assets/context_processors.py
assets/multiupload.py
assets/settings.py
assets/urls.py
assets/webp.py
assets/images/__init__.py
assets/images/actions.py
assets/images/fields.py
assets/images/forms.py
assets/images/models.py
assets/images/urls.py
assets/images/utils.py
assets/images/views.py
assets/images/widgets.py
assets/images/static/dropzone/dropzone.min.css
assets/images/static/dropzone/dropzone.min.js
assets/images/static/file-manager/file-manager.css
assets/images/static/file-manager/file-manager.js
assets/images/templates/images-form.html
assets/static/css/indents.css
assets/static/jquery/ajax-csrf.js
assets/static/jquery/jquery.ba-bbq.js
assets/templatetags/__init__.py
assets/templatetags/static_img.py
django_mp_assets.egg-info/PKG-INFO
django_mp_assets.egg-info/SOURCES.txt
django_mp_assets.egg-info/dependency_links.txt
django_mp_assets.egg-info/requires.txt
django_mp_assets.egg-info/top_level.txt