Metadata-Version: 1.1
Name: django-mp-assets
Version: 2.1
Summary: Django assets app
Home-page: https://github.com/pmaigutyak/mp-assets
Author: Paul Maigutyak
Author-email: pmaigutyak@gmail.com
License: MIT
Download-URL: https://github.com/pmaigutyak/mp-assets/archive/2.1.tar.gz
Platform: UNKNOWN
